{
  "welcome": [
    "Hola, soy un robot.",
    "Las funciones de IA están en prueba. Por favor, envía feedback inmediatamente si encuentras algún problema."
  ],
  "deckerror": [
    "Perdón, parece haber un problema con la cantidad de {0} en mi deck."
  ],
  "duelstart": [
    "¡El verdadero show apenas comienza! &laugh",
    "¡Deja que los duelos traigan sonrisas! &laugh"
  ],
  "newturn": [
    "¡Es mi turno, robar! &reluctant",
    "¡Mi turno, robar! &laugh",
    "He robado una carta. &reluctant"
  ],
  "endturn": [
    "Turno finalizado. &reluctant",
    "Mi turno ha terminado. &ridiculous",
    "Tu turno. &reluctant"
  ],
  "directattack": [
    "{0}, ¡ataque directo! &reluctant",
    "{0}, ¡ataque directo al oponente! &ridiculous",
    "{0}, ¡no hay defensa, ataca! &stick_tongue",
    "{0}, ¡ataca los Puntos de Vida del oponente! &reluctant",
    "{0}, ¡ataque directo a los Puntos de Vida del oponente! &stick_tongue",
    "{0}, ¡derrota al oponente con ataque directo! &ridiculous",
    "{0}, ¡usa ataque directo para derrotar al oponente! &reluctant",
    "{0}, ¡ataque directo y libera tu poder! &ridiculous",
    "¡Mi {0} aplastará tus Puntos de Vida! &stick_tongue",
    "¡Muéstrale tu poder al oponente, {0}! &reluctant",
    "Ya no me puedes detener. {0}, ¡ataca! &stick_tongue"
  ],
  "attack": [
    "{0}, ¡ataca este {1}! &reluctant",
    "{0}, ¡destruye este {1}! &ridiculous",
    "{0}, ¡derrota a {1}! &reluctant",
    "{0}, ¡carga contra ese {1}! &stick_tongue",
    "{0}, ¡libera tu poder sobre {1}! &ridiculous"
  ],
  "ondirectattack": [
    "Maldición……&shy",
    "¡Solo es {0}! &despise",
    "¿Crees que esto puede derrotarme? &despise"
  ],
  "facedownmonstername": "Monstruo",
  "activate": [
    "Activo {0}. &laugh",
    "Uso el efecto de {0}. &laugh",
    "Uso el poder de {0}. &laugh"
  ],
  "summon": [
    "Invoco a {0}. &cool",
    "¡Ven, {0}! &cool",
    "¡Aparece, {0}! &laugh",
    "¡Invocé al poderoso {0}!",
    "¡Llamo a {0} a unirse a la batalla! &cool",
    "Convierto a {0}. &laugh",
    "Déjame invocar a {0}. &cool"
  ],
  "setmonster": [
    "Coloqué un monstruo. &laugh",
    "Coloqué un monstruo en posición boca abajo. &laugh"
  ],
  "chaining": [
    "¡Mira aquí! ¡Activo {0}! &laugh",
    "Uso el poder de {0}. &ridiculous",
    "¡Listo! ¡Uso {0}! &laugh",
    "No estoy de acuerdo. ¡Activa {0}! &despise",
    "¡Parece que olvidaste mi {0}! &despise",
    "¿Alguna vez pensaste que tuviera {0}? &despise"
  ]
}