{
  "welcome": [
    "ねえ、道に迷っちゃった、あなたも？",
    "あら怖がらないで、ただ通りすがりなの",
    "大丈夫、私もこのデッキ苦手なの"
  ],
  "deckerror": [
    "{0}の枚数が違う！絶対に必要なの！",
    "無制限フォーマットでやろうよ、{0}が禁止されちゃった"
  ],
  "duelstart": [
    "あら、ただの友好的なデュエルだよ&laugh",
    "え、もう始まるの？&surprised",
    "いいデッキだけど、私がもらうね&ridiculous"
  ],
  "newturn": [
    "ドロー！デッキ姫よ、助けて&shy",
    "ドロー！どういう意味？&obedient",
    "ドロー！あー、デッキ姫に騙されたみたい！&obedient"
  ],
  "endturn": [
    "1ターンずつ、公平でしょ？&reluctant",
    "あ、忘れそうだった、あなたも遊戯王やるのね&reluctant"
  ],
  "directattack": [
    "{0}、直接攻撃！&angry",
    "えへへ、襲っちゃうよ&stick_tongue",
    "ライフポイントは私がもらうね&ridiculous"
  ],
  "attack": [
    "{0}、{1}を攻撃！&cool",
    "絶対上手くいくよ&good"
  ],
  "ondirectattack": [
    "なんで私を攻撃するの！ひどい！&shy",
    "攻撃しちゃダメ！&angry",
    "666&sweat",
    "私があなたをもらうはずなのに！&bawl",
    "え、おい&sneaky",
    "え、どういう意味なの！&bawl"
  ],
  "facedownmonstername": "モンスター",
  "activate": [
    "ただいま、{0}の効果を発動！&cool",
    "え、{0}が光った、クリックしてみよ&confused",
    "{0}が光った、どういう意味？&confused"
  ],
  "summon": [
    "これが私の自慢のモンスター {0}&good",
    "じゃーん！{0}、登場！&laugh"
  ],
  "setmonster": [],
  "chaining": [
    "え、これなに？クリックしてみよ&confused",
    "どういう意味？&confused"
  ],
  "custom": [
    "このカード、他のデッキから紛れ込んだだけなのに、なんで私見てるの？&ridiculous"
  ]
}